use_sqs/__init__.py
use_sqs/use_sns.py
use_sqs/use_sqs.py
use_sqs-0.1.0.dist-info/WHEEL
use_sqs-0.1.0.dist-info/METADATA
use_sqs-0.1.0.dist-info/RECORD
