Metadata-Version: 2.3
Name: use-sqs
Version: 0.1.0
Summary: A library for using AWS SQS and SNS
Author: miclon
Author-email: miclon <jcnd@163.com>
Requires-Dist: boto3>=1.37.38
Requires-Dist: typing-extensions>=4.1.0
Requires-Dist: pytest>=7.0.0 ; extra == 'test'
Requires-Dist: pytest-asyncio>=0.21.0 ; extra == 'test'
Requires-Python: >=3.8
Provides-Extra: test
